[
    {
        "word": "Ephemeral",
        "definition": "Lasting for a very short time"
    },
    {
        "word": "Serendipity",
        "definition": "The occurrence and development of events by chance in a happy or beneficial way"
    },
    {
        "word": "Mellifluous",
        "definition": "A sound that is sweet and smooth, pleasing to hear"
    },
    {
        "word": "Ineffable",
        "definition": "Too great or extreme to be expressed or described in words"
    },
    {
        "word": "Petrichor",
        "definition": "A pleasant smell that frequently accompanies the first rain after a long period of warm, dry weather"
    },
    {
        "word": "Limerence",
        "definition": "The state of being infatuated or obsessed with another person"
    },
    {
        "word": "Sonder",
        "definition": "The realization that each random passerby is living a life as vivid and complex as your own"
    },
    {
        "word": "Vellichor",
        "definition": "The strange wistfulness of used bookstores"
    },
    {
        "word": "Solitude",
        "definition": "The state or situation of being alone"
    },
    {
        "word": "Aurora",
        "definition": "A natural electrical phenomenon characterized by the appearance of streamers of reddish or greenish light in the sky"
    }
]